lwbna_unet/LWBNA_Unet.py
lwbna_unet/__init__.py
lwbna_unet-1.0.2.dist-info/LICENSE
lwbna_unet-1.0.2.dist-info/METADATA
lwbna_unet-1.0.2.dist-info/WHEEL
lwbna_unet-1.0.2.dist-info/top_level.txt
lwbna_unet-1.0.2.dist-info/RECORD
