Metadata-Version: 2.1
Name: lwbna-unet
Version: 1.0.2
Summary: TF2 (Keras) implementation of LWBNA_Unet. Unrelated to the authors of the paper
Home-page: https://github.com/fcossio/LWBNA_Unet
Author: Fernando Cossio
Author-email: fer_cossio@hotmail.com
Project-URL: Bug Reports, https://github.com/fcossio/LWBNA_Unet/issues
Project-URL: Source, https://github.com/pypa/sampleproject/
Keywords: tensorflow2,tf2,keras,image segmentation,computer vision,unet
Requires-Python: >=3.6
License-File: LICENSE
Requires-Dist: keras
